quantifyML/__init__.py
quantifyML/base.py
quantifyML/model_selection.py
quantifyML/classification/__init__.py
quantifyML/classification/pwkclf.py
quantifyML/evaluation/__init__.py
quantifyML/evaluation/measures/__init__.py
quantifyML/evaluation/measures/ae.py
quantifyML/evaluation/measures/bias.py
quantifyML/evaluation/measures/kld.py
quantifyML/evaluation/measures/mse.py
quantifyML/evaluation/measures/nae.py
quantifyML/evaluation/measures/nkld.py
quantifyML/evaluation/measures/nrae.py
quantifyML/evaluation/measures/rae.py
quantifyML/evaluation/measures/se.py
quantifyML/evaluation/protocol/_Protocol.py
quantifyML/evaluation/protocol/__init__.py
quantifyML/evaluation/protocol/app.py
quantifyML/evaluation/protocol/npp.py
quantifyML/methods/__init__.py
quantifyML/methods/aggregative/__init__.py
quantifyML/methods/aggregative/cc.py
quantifyML/methods/aggregative/emq.py
quantifyML/methods/aggregative/fm.py
quantifyML/methods/aggregative/gac.py
quantifyML/methods/aggregative/gpac.py
quantifyML/methods/aggregative/pcc.py
quantifyML/methods/aggregative/pwk.py
quantifyML/methods/aggregative/ThreholdOptm/_ThreholdOptimization.py
quantifyML/methods/aggregative/ThreholdOptm/__init__.py
quantifyML/methods/aggregative/ThreholdOptm/acc.py
quantifyML/methods/aggregative/ThreholdOptm/max.py
quantifyML/methods/aggregative/ThreholdOptm/ms.py
quantifyML/methods/aggregative/ThreholdOptm/ms2.py
quantifyML/methods/aggregative/ThreholdOptm/pacc.py
quantifyML/methods/aggregative/ThreholdOptm/t50.py
quantifyML/methods/aggregative/ThreholdOptm/x.py
quantifyML/methods/aggregative/mixtureModels/_MixtureModel.py
quantifyML/methods/aggregative/mixtureModels/__init__.py
quantifyML/methods/aggregative/mixtureModels/dys.py
quantifyML/methods/aggregative/mixtureModels/dys_syn.py
quantifyML/methods/aggregative/mixtureModels/hdy.py
quantifyML/methods/aggregative/mixtureModels/smm.py
quantifyML/methods/aggregative/mixtureModels/sord.py
quantifyML/methods/meta/__init__.py
quantifyML-0.0.11.dist-info/METADATA
quantifyML-0.0.11.dist-info/WHEEL
quantifyML-0.0.11.dist-info/top_level.txt
quantifyML-0.0.11.dist-info/RECORD
